ShujuKexueHeRengongzhinengJishuBiji/README.md
ShujuKexueHeRengongzhinengJishuBiji/__init__.py
ShujuKexueHeRengongzhinengJishuBiji/__main__.py
ShujuKexueHeRengongzhinengJishuBiji/file.epub
ShujuKexueHeRengongzhinengJishuBiji/index.html
ShujuKexueHeRengongzhinengJishuBiji/css/__init__.py
ShujuKexueHeRengongzhinengJishuBiji/css/annotations.css
ShujuKexueHeRengongzhinengJishuBiji/css/main.css
ShujuKexueHeRengongzhinengJishuBiji/css/normalize.css
ShujuKexueHeRengongzhinengJishuBiji/css/popup.css
ShujuKexueHeRengongzhinengJishuBiji/font/__init__.py
ShujuKexueHeRengongzhinengJishuBiji/font/fontello.eot
ShujuKexueHeRengongzhinengJishuBiji/font/fontello.svg
ShujuKexueHeRengongzhinengJishuBiji/font/fontello.ttf
ShujuKexueHeRengongzhinengJishuBiji/font/fontello.woff
ShujuKexueHeRengongzhinengJishuBiji/img/__init__.py
ShujuKexueHeRengongzhinengJishuBiji/img/annotator-glyph-sprite.png
ShujuKexueHeRengongzhinengJishuBiji/img/annotator-icon-sprite.png
ShujuKexueHeRengongzhinengJishuBiji/img/apple-touch-icon.png
ShujuKexueHeRengongzhinengJishuBiji/img/cancelfullscreen.png
ShujuKexueHeRengongzhinengJishuBiji/img/close.png
ShujuKexueHeRengongzhinengJishuBiji/img/fullscreen.png
ShujuKexueHeRengongzhinengJishuBiji/img/loader.gif
ShujuKexueHeRengongzhinengJishuBiji/img/menu-icon.png
ShujuKexueHeRengongzhinengJishuBiji/img/save.png
ShujuKexueHeRengongzhinengJishuBiji/img/saved.png
ShujuKexueHeRengongzhinengJishuBiji/img/settings-s.png
ShujuKexueHeRengongzhinengJishuBiji/img/settings.png
ShujuKexueHeRengongzhinengJishuBiji/img/star.png
ShujuKexueHeRengongzhinengJishuBiji/js/__init__.py
ShujuKexueHeRengongzhinengJishuBiji/js/epub.js
ShujuKexueHeRengongzhinengJishuBiji/js/epub.min.js
ShujuKexueHeRengongzhinengJishuBiji/js/epub.min.map
ShujuKexueHeRengongzhinengJishuBiji/js/hooks.min.js
ShujuKexueHeRengongzhinengJishuBiji/js/hooks.min.map
ShujuKexueHeRengongzhinengJishuBiji/js/reader.js
ShujuKexueHeRengongzhinengJishuBiji/js/reader.js.map
ShujuKexueHeRengongzhinengJishuBiji/js/reader.min.js
shuju_kexue_he_rengongzhineng_jishu_biji-2024.3.5.0.dist-info/METADATA
shuju_kexue_he_rengongzhineng_jishu_biji-2024.3.5.0.dist-info/WHEEL
shuju_kexue_he_rengongzhineng_jishu_biji-2024.3.5.0.dist-info/entry_points.txt
shuju_kexue_he_rengongzhineng_jishu_biji-2024.3.5.0.dist-info/top_level.txt
shuju_kexue_he_rengongzhineng_jishu_biji-2024.3.5.0.dist-info/RECORD
